bubbypdf/__init__.py
bubbypdf/bubbypdf.py
bubbypdf-0.0.3.dist-info/LICENSE
bubbypdf-0.0.3.dist-info/METADATA
bubbypdf-0.0.3.dist-info/WHEEL
bubbypdf-0.0.3.dist-info/entry_points.txt
bubbypdf-0.0.3.dist-info/top_level.txt
bubbypdf-0.0.3.dist-info/RECORD
